HW/HW2/adder.v
//define gates with delays
`define AND and #50
`define OR or #50
`define XOR xor #50

module behavioralFullAdder(sum, carryout, a, b, carryin);
	output sum, carryout;
	input a, b, carryin;
	assign {carryout, sum}=a+b+carryin;
endmodule

module structuralFullAdder(out, carryout, a, b, carryin);
	output out, carryout;
	input a, b, carryin;

	wire AxorB;
	wire CinandAxorB;
	wire AandB;

	`XOR(AxorB, a, b);
	`XOR(out, AxorB, carryin);
	`AND(CinandAxorB, AxorB, carryin);
	`AND(AandB, a, b);
	`OR(carryout, CinandAxorB, AandB);
endmodule

module testFullAdder;
	reg a, b, carryin;
	wire sum, carryout;
	// behavioralFullAdder adder (sum, carryout, a, b, carryin);
	structuralFullAdder adder (sum, carryout, a, b, carryin);
	 
	initial begin
		$dumpfile("adder.vcd");
		$dumpvars(0, testFullAdder);

		$display("A B Cin | S Cout | Expected Output");
		a=0;b=0;carryin=0; #1000
		$display("%b  %b  %b | %b   %b  | All false", a, b, carryin, sum, carryout);
		a=0;b=0;carryin=1; #1000
		$display("%b  %b  %b | %b   %b  | S only", a, b, carryin, sum, carryout);
		a=0;b=1;carryin=0; #1000
		$display("%b  %b  %b | %b   %b  | S only", a, b, carryin, sum, carryout);
		a=0;b=1;carryin=1; #1000
		$display("%b  %b  %b | %b   %b  | Cout only", a, b, carryin, sum, carryout);
		a=1;b=0;carryin=0; #1000
		$display("%b  %b  %b | %b   %b  | S only", a, b, carryin, sum, carryout);
		a=1;b=0;carryin=1; #1000
		$display("%b  %b  %b | %b   %b  | Cout only", a, b, carryin, sum, carryout);
		a=1;b=1;carryin=0; #1000
		$display("%b  %b  %b | %b   %b  | Cout only", a, b, carryin, sum, carryout);
		a=1;b=1;carryin=1; #1000
		$display("%b  %b  %b | %b   %b  | Both", a, b, carryin, sum, carryout);
	end
endmodule

HW/HW2/adder.vcd
$date
	Fri Sep 25 11:42:29 2015
$end
$version
	Icarus Verilog
$end
$timescale
	1s
$end
$scope module testFullAdder $end
$var wire 1 ! carryout $end
$var wire 1 " sum $end
$var reg 1 # a $end
$var reg 1 $ b $end
$var reg 1 % carryin $end
$scope module adder $end
$var wire 1 & AandB $end
$var wire 1 ' AxorB $end
$var wire 1 ( CinandAxorB $end
$var wire 1 ) a $end
$var wire 1 * b $end
$var wire 1 + carryin $end
$var wire 1 ! carryout $end
$var wire 1 " out $end
$upscope $end
$upscope $end
$enddefinitions $end
#0
$dumpvars
0+
0*
0)
z(
z'
z&
0%
0$
0#
x"
x!
$end
#50
0&
0(
0'
#100
0!
0"
#1000
1%
1+
#1050
1"
#2000
0%
0+
1$
1*
#2050
0"
1'
#2100
1"
#3000
1%
1+
#3050
0"
1(
#3100
1!
#4000
0%
0+
0$
0*
1#
1)
#4050
1"
0(
#4100
0!
#5000
1%
1+
#5050
0"
1(
#5100
1!
#6000
0%
0+
1$
1*
#6050
1"
0(
0'
1&
#6100
0"
#7000
1%
1+
#7050
1"
