HW/HW2/decoder.v
//define gates with delays
`define AND and #50
`define NOT not #50

module behavioralDecoder(out0,out1,out2,out3, address0,address1, enable);
	output out0, out1, out2, out3;
	input address0, address1;
	input enable;
	assign {out3,out2,out1,out0}=enable<<{address1,address0};
endmodule

module structuralDecoder(out0,out1,out2,out3, address0,address1, enable);
	output out0, out1, out2, out3;
	input address0, address1;
	input enable;

	wire nA0;
	wire nA1;
	wire nA0andnA1;
	wire A0andnA1;
	wire nA0andA1;
	wire A0andA1;

	`NOT(nA0, address0);
	`NOT(nA1, address1);
	`AND(nA0andnA1, nA0, nA1);
	`AND(A0andnA1, address0, nA1);
	`AND(nA0andA1, nA0, address1);
	`AND(A0andA1, address0, address1);

	//enable
	`AND(out0, nA0andnA1, enable);
	`AND(out1, A0andnA1, enable);
	`AND(out2, nA0andA1, enable);
	`AND(out3, A0andA1, enable);
endmodule

module testDecoder; 
	reg addr0, addr1;
	reg enable;
	wire out0,out1,out2,out3;
	//behavioralDecoder decoder (out0,out1,out2,out3,addr0,addr1,enable);
	structuralDecoder decoder (out0,out1,out2,out3,addr0,addr1,enable); // Swap after testing

	initial begin
		$dumpfile("decoder.vcd");
		$dumpvars(0, testDecoder);

		$display("En A0 A1| O0 O1 O2 O3 | Expected Output");
		enable=0;addr0=0;addr1=0; #1000 
		$display("%b  %b  %b |  %b  %b  %b  %b | All false", enable, addr0, addr1, out0, out1, out2, out3);
		enable=0;addr0=1;addr1=0; #1000
		$display("%b  %b  %b |  %b  %b  %b  %b | All false", enable, addr0, addr1, out0, out1, out2, out3);
		enable=0;addr0=0;addr1=1; #1000 
		$display("%b  %b  %b |  %b  %b  %b  %b | All false", enable, addr0, addr1, out0, out1, out2, out3);
		enable=0;addr0=1;addr1=1; #1000 
		$display("%b  %b  %b |  %b  %b  %b  %b | All false", enable, addr0, addr1, out0, out1, out2, out3);
		enable=1;addr0=0;addr1=0; #1000 
		$display("%b  %b  %b |  %b  %b  %b  %b | O0 Only", enable, addr0, addr1, out0, out1, out2, out3);
		enable=1;addr0=1;addr1=0; #1000 
		$display("%b  %b  %b |  %b  %b  %b  %b | O1 Only", enable, addr0, addr1, out0, out1, out2, out3);
		enable=1;addr0=0;addr1=1; #1000 
		$display("%b  %b  %b |  %b  %b  %b  %b | O2 Only", enable, addr0, addr1, out0, out1, out2, out3);
		enable=1;addr0=1;addr1=1; #1000 
		$display("%b  %b  %b |  %b  %b  %b  %b | O3 Only", enable, addr0, addr1, out0, out1, out2, out3);
	end
endmodule

HW/HW2/decoder.vcd
$date
	Fri Sep 25 11:42:29 2015
$end
$version
	Icarus Verilog
$end
$timescale
	1s
$end
$scope module testDecoder $end
$var wire 1 ! out0 $end
$var wire 1 " out1 $end
$var wire 1 # out2 $end
$var wire 1 $ out3 $end
$var reg 1 % addr0 $end
$var reg 1 & addr1 $end
$var reg 1 ' enable $end
$scope module decoder $end
$var wire 1 ( A0andA1 $end
$var wire 1 ) A0andnA1 $end
$var wire 1 * address0 $end
$var wire 1 + address1 $end
$var wire 1 , enable $end
$var wire 1 - nA0 $end
$var wire 1 . nA0andA1 $end
$var wire 1 / nA0andnA1 $end
$var wire 1 0 nA1 $end
$var wire 1 ! out0 $end
$var wire 1 " out1 $end
$var wire 1 # out2 $end
$var wire 1 $ out3 $end
$upscope $end
$upscope $end
$enddefinitions $end
#0
$dumpvars
z0
x/
z.
z-
0,
0+
0*
z)
z(
0'
0&
0%
z$
z#
z"
z!
$end
#50
0$
0#
0"
0!
0(
0.
0)
1-
10
#100
1/
#1000
1%
1*
#1050
0-
1)
#1100
0/
#2000
1&
1+
0%
0*
#2050
00
1-
0)
#2100
1.
#3000
1%
1*
#3050
0-
1(
#3100
0.
#4000
0&
0+
0%
0*
1'
1,
#4050
10
1-
0(
1$
#4100
1/
0$
#4150
1!
#5000
1%
1*
#5050
0-
1)
#5100
0/
1"
#5150
0!
#6000
1&
1+
0%
0*
#6050
00
1-
0)
#6100
1.
0"
#6150
1#
#7000
1%
1*
#7050
0-
1(
#7100
0.
1$
#7150
0#
