HW/HW2/multiplexer.v
//define gates with delays
`define AND and #50
`define OR or #50
`define NOT not #50

module behavioralMultiplexer(out, address0,address1, in0,in1,in2,in3);
	output out;
	input address0, address1;
	input in0, in1, in2, in3;
	wire[3:0] inputs = {in3, in2, in1, in0};
	wire[1:0] address = {address1, address0};
	assign out = inputs[address];
endmodule

module structuralMultiplexer(out, address0,address1, in0,in1,in2,in3);
	output out;
	input address0, address1;
	input in0, in1, in2, in3;

	wire nA0;
	wire nA1;
	wire I0andnA0andnA1;
	wire I1andA0andnA1;
	wire I2andnA0andA1;
	wire I3andA0andA1;

	`NOT(nA0, address0);
	`NOT(nA1, address1);

	`AND(I0andnA0andnA1, in0, nA0, nA1);
	`AND(I1andA0andnA1, in1, address0, nA1);
	`AND(I2andnA0andA1, in2, nA0, address1);
	`AND(I3andA0andA1, in3, address0, address1);

	`OR(out, I0andnA0andnA1, I1andA0andnA1, I2andnA0andA1, I3andA0andA1);


endmodule


module testMultiplexer;
	reg address0, address1;
	reg in0, in1, in2, in3;
	wire out;
	// behavioralMultiplexer multiplexer (out,address0,address1,in0,in1,in2,in3);
	structuralMultiplexer multiplexer (out,address0,address1,in0,in1,in2,in3);
	initial begin
		$dumpfile("multiplexer.vcd");
		$dumpvars(0, testMultiplexer);

		$display("A1 A0 | I3 I2 I1 I0 | Out | Expected Output");
		address1=0;address0=0;in3=1'bX;in2=1'bX;in1=1'bX;in0=0; #1000
		$display("%b  %b  | %b  %b  %b  %b  |  %b  | false", address1, address0, in3, in2, in1, in0, out);
		address1=0;address0=0;in3=1'bX;in2=1'bX;in1=1'bX;in0=1; #1000
		$display("%b  %b  | %b  %b  %b  %b  |  %b  | true", address1, address0, in3, in2, in1, in0, out);
		address1=0;address0=1;in3=1'bX;in2=1'bX;in1=0;in0=1'bX; #1000
		$display("%b  %b  | %b  %b  %b  %b  |  %b  | false", address1, address0, in3, in2, in1, in0, out);
		address1=0;address0=1;in3=1'bX;in2=1'bX;in1=1;in0=1'bX; #1000
		$display("%b  %b  | %b  %b  %b  %b  |  %b  | true", address1, address0, in3, in2, in1, in0, out);
		address1=1;address0=0;in3=1'bX;in2=0;in1=1'bX;in0=1'bX; #1000
		$display("%b  %b  | %b  %b  %b  %b  |  %b  | false", address1, address0, in3, in2, in1, in0, out);
		address1=1;address0=0;in3=1'bX;in2=1;in1=1'bX;in0=1'bX; #1000
		$display("%b  %b  | %b  %b  %b  %b  |  %b  | true", address1, address0, in3, in2, in1, in0, out);
		address1=1;address0=1;in3=0;in2=1'bX;in1=1'bX;in0=1'bX; #1000
		$display("%b  %b  | %b  %b  %b  %b  |  %b  | false", address1, address0, in3, in2, in1, in0, out);
		address1=1;address0=1;in3=1;in2=1'bX;in1=1'bX;in0=1'bX; #1000
		$display("%b  %b  | %b  %b  %b  %b  |  %b  | true", address1, address0, in3, in2, in1, in0, out);
	end
endmodule

HW/HW2/multiplexer.vcd
$date
	Fri Sep 25 11:42:29 2015
$end
$version
	Icarus Verilog
$end
$timescale
	1s
$end
$scope module testMultiplexer $end
$var wire 1 ! out $end
$var reg 1 " address0 $end
$var reg 1 # address1 $end
$var reg 1 $ in0 $end
$var reg 1 % in1 $end
$var reg 1 & in2 $end
$var reg 1 ' in3 $end
$scope module multiplexer $end
$var wire 1 ( I0andnA0andnA1 $end
$var wire 1 ) I1andA0andnA1 $end
$var wire 1 * I2andnA0andA1 $end
$var wire 1 + I3andA0andA1 $end
$var wire 1 , address0 $end
$var wire 1 - address1 $end
$var wire 1 . in0 $end
$var wire 1 / in1 $end
$var wire 1 0 in2 $end
$var wire 1 1 in3 $end
$var wire 1 2 nA0 $end
$var wire 1 3 nA1 $end
$var wire 1 ! out $end
$upscope $end
$upscope $end
$enddefinitions $end
#0
$dumpvars
z3
z2
x1
x0
x/
0.
0-
0,
z+
z*
z)
z(
x'
x&
x%
0$
0#
0"
z!
$end
#50
0+
0*
0)
0(
12
13
#100
0!
#1000
1$
1.
#1050
1(
#1100
1!
#2000
x$
x.
0%
0/
1"
1,
#2050
x(
02
#2100
x!
0(
#2150
0!
#3000
1%
1/
#3050
1)
#3100
1!
#4000
x%
x/
0&
00
0"
0,
1#
1-
#4050
12
0)
03
#4100
0!
#5000
1&
10
#5050
1*
#5100
1!
#6000
x&
x0
0'
01
1"
1,
#6050
x*
02
#6100
x!
0*
#6150
0!
#7000
1'
11
#7050
1+
#7100
1!
